README.rst
setup.cfg
setup.py
Pyreboot/__init__.py
Pyreboot/_reboot.pyx
Pyreboot.egg-info/PKG-INFO
Pyreboot.egg-info/SOURCES.txt
Pyreboot.egg-info/dependency_links.txt
Pyreboot.egg-info/not-zip-safe
Pyreboot.egg-info/top_level.txt