Metadata-Version: 1.1
Name: Pyreboot
Version: 1.0
Summary: small python library, that allow developers to rebootpower off, others..  a computer as easy as it sounds
Home-page: https://github.com/leoxnidas/Pyreboot
Author: Leonardo Javier Esparis Meza
Author-email: leoxnidas.c.14@gmail.com
License: BSD
Download-URL: https://github.com/leoxnidas/Pyreboot
Keywords: reboot rebooter trollrebooter gtkrebooter
Platform: linux
Classifier: Development Status :: 5 - Production/Stable
Classifier: Intended Audience :: Developers
Classifier: License :: OSI Approved :: BSD License
Classifier: Operating System :: OS Independent
Classifier: Programming Language :: Python
Classifier: Programming Language :: Python :: 2
Classifier: Programming Language :: Python :: 2.3
Classifier: Programming Language :: Python :: 2.4
Classifier: Programming Language :: Python :: 2.5
Classifier: Programming Language :: Python :: 2.6
Classifier: Programming Language :: Python :: 2.7
Classifier: Programming Language :: Python :: 3
Classifier: Programming Language :: Python :: 3.0
Classifier: Programming Language :: Python :: 3.1
Classifier: Programming Language :: Python :: 3.2
Classifier: Programming Language :: Python :: 3.3
Classifier: Programming Language :: Python :: 3.4
Classifier: Programming Language :: Python :: 3.5
Classifier: Programming Language :: Python :: 3.6
Classifier: Topic :: Software Development :: Libraries
Classifier: Topic :: Software Development :: Libraries :: Python Modules
